huma_utils/__init__.py
huma_utils/async_utils.py
huma_utils/auth_utils.py
huma_utils/chain_utils.py
huma_utils/constants.py
huma_utils/datetime_utils.py
huma_utils/py.typed
huma_utils/pydantic_utils.py
huma_utils/request_utils.py
huma_utils/string_utils.py
huma_utils/test_helpers/__init__.py
huma_utils/test_helpers/address_helpers.py
huma_utils/test_helpers/api_test_helpers.py
huma_utils/test_helpers/vcr_helpers.py
huma_utils/web3_utils.py
huma_utils-0.17.0.dist-info/METADATA
huma_utils-0.17.0.dist-info/WHEEL
huma_utils-0.17.0.dist-info/licenses/LICENSE
huma_utils-0.17.0.dist-info/RECORD
